LICENSE
MANIFEST.in
README.md
setup.py
keras_gradient_noise/__init__.py
keras_gradient_noise/gradient_noise.py
keras_gradient_noise.egg-info/PKG-INFO
keras_gradient_noise.egg-info/SOURCES.txt
keras_gradient_noise.egg-info/dependency_links.txt
keras_gradient_noise.egg-info/not-zip-safe
keras_gradient_noise.egg-info/requires.txt
keras_gradient_noise.egg-info/top_level.txt