Metadata-Version: 1.1
Name: keras-gradient-noise
Version: 0.11
Summary: Gradient Noise for Keras
Home-page: https://github.com/cpury/keras_gradient_noise
Author: Max Schumacher
Author-email: max@maxschumacher.info
License: MIT
Platform: UNKNOWN
Classifier: Development Status :: 3 - Alpha
Classifier: License :: OSI Approved :: MIT License
Classifier: Programming Language :: Python
Classifier: Topic :: Scientific/Engineering :: Artificial Intelligence
Classifier: Intended Audience :: Developers
Classifier: Intended Audience :: Education
Classifier: Intended Audience :: Science/Research
Classifier: Topic :: Software Development :: Libraries
Classifier: Topic :: Software Development :: Libraries :: Python Modules
